jason/__init__.py
jason/errors.py
jason/flags.py
jason/jason.py
jason_cmd-0.0.4.dist-info/LICENSE
jason_cmd-0.0.4.dist-info/METADATA
jason_cmd-0.0.4.dist-info/WHEEL
jason_cmd-0.0.4.dist-info/top_level.txt
jason_cmd-0.0.4.dist-info/RECORD
