Metadata-Version: 2.1
Name: jason-cmd
Version: 0.0.4
Summary: Shell command manager and flag handler.
Home-page: https://github.com/ilpg/jason
Author: ilpg 
Author-email: chrismdjr@gmail.com
License: UNKNOWN
Platform: UNKNOWN
Classifier: Programming Language :: Python :: 3
Classifier: License :: OSI Approved :: MIT License
Classifier: Operating System :: OS Independent
Requires-Python: >=3.6
